{
	"variants": {
		"cor=1,facing=north": { "model": "chinjufumod:block_tabakaya", "y": 90 },
		"cor=1,facing=south": { "model": "chinjufumod:block_tabakaya", "y": 270 },
		"cor=1,facing=west" : { "model": "chinjufumod:block_tabakaya", "y": 0 },
    	"cor=1,facing=east" : { "model": "chinjufumod:block_tabakaya", "y": 180 },
		"cor=2,facing=north": { "model": "chinjufumod:block_tabakaya_cor", "y": 180 },
		"cor=2,facing=south": { "model": "chinjufumod:block_tabakaya_cor", "y": 0 },
		"cor=2,facing=west" : { "model": "chinjufumod:block_tabakaya_cor", "y": 90 },
		"cor=2,facing=east" : { "model": "chinjufumod:block_tabakaya_cor", "y": 270 }
	}
}
